vedro_httpx/__init__.py
vedro_httpx/__main__.py
vedro_httpx/_async_http_interface.py
vedro_httpx/_response.py
vedro_httpx/_response_renderer.py
vedro_httpx/_sync_http_interface.py
vedro_httpx/_vedro_httpx.py
vedro_httpx/_version.py
vedro_httpx/py.typed
vedro_httpx/recorder/__init__.py
vedro_httpx/recorder/_async_har_formatter.py
vedro_httpx/recorder/_base_har_formatter.py
vedro_httpx/recorder/_har_builder.py
vedro_httpx/recorder/_request_recorder.py
vedro_httpx/recorder/_sync_har_formatter.py
vedro_httpx/recorder/har/__init__.py
vedro_httpx/spec_generator/__init__.py
vedro_httpx/spec_generator/_api_spec_builder.py
vedro_httpx/spec_generator/_har_reader.py
vedro_httpx/spec_generator/_open_api_spec_generator.py
vedro_httpx/spec_generator/_utils.py
vedro_httpx/spec_generator/model/__init__.py
vedro_httpx/spec_generator/model/_formatter.py
vedro_httpx/spec_generator/model/_json_schema.py
vedro_httpx/spec_generator/model/_merger.py
vedro_httpx/spec_generator/model/_nodes.py
vedro_httpx/spec_generator/model/_visitor.py
vedro_httpx-0.8.1.dist-info/licenses/LICENSE
vedro_httpx-0.8.1.dist-info/METADATA
vedro_httpx-0.8.1.dist-info/WHEEL
vedro_httpx-0.8.1.dist-info/entry_points.txt
vedro_httpx-0.8.1.dist-info/top_level.txt
vedro_httpx-0.8.1.dist-info/RECORD
