Metadata-Version: 2.4
Name: vedro-httpx
Version: 0.8.1
Summary: Vedro + HTTPX
Home-page: https://github.com/vedro-universe/vedro-httpx
Author: Nikita Tsvetkov
Author-email: tsv1@fastmail.com
License: Apache-2.0
Project-URL: Docs, https://vedro.io/docs/integrations/httpx-client
Project-URL: GitHub, https://github.com/vedro-universe/vedro-httpx
Classifier: License :: OSI Approved :: Apache Software License
Classifier: Programming Language :: Python :: 3.8
Classifier: Programming Language :: Python :: 3.9
Classifier: Programming Language :: Python :: 3.10
Classifier: Programming Language :: Python :: 3.11
Classifier: Programming Language :: Python :: 3.12
Classifier: Typing :: Typed
Requires-Python: >=3.8
License-File: LICENSE
Requires-Dist: httpx<1.0,>=0.24
Requires-Dist: vedro<2.0,>=1.7
Requires-Dist: PyYAML<7.0,>6.0
Dynamic: author
Dynamic: author-email
Dynamic: classifier
Dynamic: description
Dynamic: description-content-type
Dynamic: home-page
Dynamic: license
Dynamic: license-file
Dynamic: project-url
Dynamic: requires-dist
Dynamic: requires-python
Dynamic: summary
